
[
    {
        "id": 1,
        "name": "Origins: Tales of Eri",
        "image": "/Origins.png",
        "description": "Game Development, UI/UX Design, Virtual Reality"
    },
    {
        "id": 1,
        "name": "BuildAR",
        "image": "/BuildAR.png",
        "description": "Game Development, UI/UX Design, Virtual Reality"
    },
   
    {
        "id": 1,
        "name": "Friday",
        "image": "/Friday.png",
        "description": "Game Development, UI/UX Design, Virtual Reality"
    },
    {
        "id": 1,
        "name": "Wyrewolf",
        "image": "/Wyrewolf.png",
        "description": "Game Development, UI/UX Design, Virtual Reality"
    },
    {
        "id": 1,
        "name": "Scoff",
        "image": "/Scoff.png",
        "description": "Game Development, UI/UX Design, Virtual Reality"
    },
    {
        "id": 1,
        "name": "SafeSpace",
        "image": "/SafeSpace.png",
        "description": "Game Development, UI/UX Design, Virtual Reality"
    }
    
]